capture_hc/__init__.py
capture_hc/honeycomb_client.py
capture_hc-0.2.0.dist-info/licenses/LICENSE
capture_hc-0.2.0.dist-info/METADATA
capture_hc-0.2.0.dist-info/WHEEL
capture_hc-0.2.0.dist-info/top_level.txt
capture_hc-0.2.0.dist-info/RECORD
