Metadata-Version: 2.4
Name: capture_hc
Version: 0.2.0
Summary: A simple, user-friendly Python client for sending events and traces to Honeycomb, with connection management and decorator support for timing and custom fields.
Home-page: https://github.com/yourusername/capture_hc
Author: Amit Singh Sansoya
Author-email: tusharamit@yahoo.com
Maintainer: Amit Singh Sansoya
Maintainer-email: tusharamit@yahoo.com
Classifier: Programming Language :: Python :: 3
Classifier: License :: OSI Approved :: MIT License
Classifier: Operating System :: OS Independent
Classifier: Intended Audience :: Developers
Classifier: Topic :: Software Development :: Libraries :: Python Modules
Requires-Python: >=3.6
License-File: LICENSE
Requires-Dist: libhoney
Dynamic: author
Dynamic: author-email
Dynamic: classifier
Dynamic: description
Dynamic: description-content-type
Dynamic: home-page
Dynamic: license-file
Dynamic: maintainer
Dynamic: maintainer-email
Dynamic: requires-dist
Dynamic: requires-python
Dynamic: summary
